akademy/__init__.py
akademy/common/__init__.py
akademy/common/project_paths.py
akademy/common/typedefs.py
akademy/common/utils.py
akademy/models/__init__.py
akademy/models/experience_replay_memory.py
akademy/models/ohlcv.py
akademy/models/trade.py
akademy/models/trade_action.py
akademy/models/agents/__init__.py
akademy/models/agents/dqn_agent.py
akademy/models/base_models/__init__.py
akademy/models/base_models/agent.py
akademy/models/base_models/epsilon_greedy.py
akademy/models/base_models/network_base.py
akademy/models/base_models/replay_memory.py
akademy/models/base_models/trade_env_base.py
akademy/models/envs/__init__.py
akademy/models/envs/trade_env.py
akademy/models/networks/__init__.py
akademy/models/networks/three_layer_linear.py
tests/__init__.py
tests/test_data.py
tests/test_envs.py
akademy-0.1.51.dist-info/LICENSE
akademy-0.1.51.dist-info/METADATA
akademy-0.1.51.dist-info/WHEEL
akademy-0.1.51.dist-info/top_level.txt
akademy-0.1.51.dist-info/RECORD
