Metadata-Version: 2.1
Name: akademy
Version: 0.1.51
Summary: akademy: A Reinforcement Learning Framework
Home-page: https://github.com/alphazwest/akademy
Author: Zack West
Author-email: Zack West <alphazwest@gmail.com>
License: BSD-3-Clause
Project-URL: Homepage, https://github.com/alphazwest/akademy
Project-URL: Bug Tracker, https://github.com/alphazwest/akademy/issues
Keywords: reinforcement learning,quantitative trading,fintech,trading bot,algorithmic trading,finance,automated trading,neural networks,artificial intelligence,machine learning
Classifier: Development Status :: 3 - Alpha
Classifier: Topic :: Scientific/Engineering :: Artificial Intelligence
Classifier: License :: OSI Approved :: BSD License
Classifier: Programming Language :: Python :: 3
Classifier: Programming Language :: Python :: 3.7
Classifier: Programming Language :: Python :: 3.8
Classifier: Programming Language :: Python :: 3.9
Classifier: Programming Language :: Python :: 3.10
Classifier: Operating System :: OS Independent
Classifier: Natural Language :: English
Classifier: Intended Audience :: Financial and Insurance Industry
Classifier: Intended Audience :: Developers
Classifier: Intended Audience :: Science/Research
Classifier: Environment :: GPU :: NVIDIA CUDA :: 11.7
Provides: akademy
Requires-Python: >=3.7
License-File: LICENSE
Requires-Dist: pandas (==1.5.2)
Requires-Dist: torch (==1.13.1)
Requires-Dist: gymnasium (==0.27.0)
